gofastapi/__init__.py
gofastapi/ai.py
gofastapi/core.py
gofastapi/version.py
gofastapi/websocket.py
gofastapi/ai_debugger/__init__.py
gofastapi/ai_debugger/interactive.py
gofastapi/ai_debugger/translator.py
gofastapi/cli/__init__.py
gofastapi/cli/commands.py
gofastapi/cli/gofastapi_cli.py
gofastapi/monitoring/__init__.py
gofastapi/monitoring/health.py
gofastapi/monitoring/metrics.py
gofastapi/runtime/__init__.py
gofastapi/runtime/bridge.py
gofastapi/runtime/hot_reload.py
gofastapi/runtime/subinterpreter.py
gofastapi-1.0.3.dist-info/licenses/LICENSE
gofastapi-1.0.3.dist-info/METADATA
gofastapi-1.0.3.dist-info/WHEEL
gofastapi-1.0.3.dist-info/entry_points.txt
gofastapi-1.0.3.dist-info/top_level.txt
gofastapi-1.0.3.dist-info/RECORD
