Metadata-Version: 2.4
Name: gofastapi
Version: 1.0.3
Summary: The fastest Python web framework - A drop-in FastAPI replacement with 25x performance boost!
Author-email: GoFastAPI Team <support@gofastapi.dev>
Maintainer-email: GoFastAPI Team <support@gofastapi.dev>
License: MIT
Project-URL: Homepage, https://github.com/coffeecms/gofastapi
Project-URL: Documentation, https://docs.gofastapi.dev
Project-URL: Repository, https://github.com/coffeecms/gofastapi
Project-URL: Bug Tracker, https://github.com/coffeecms/gofastapi/issues
Project-URL: Changelog, https://github.com/coffeecms/gofastapi/blob/main/CHANGELOG.md
Project-URL: Funding, https://github.com/sponsors/coffeecms
Keywords: fastapi,web,framework,api,fast,performance,async,rest,http,server,microservice,python,go
Classifier: Development Status :: 5 - Production/Stable
Classifier: Intended Audience :: Developers
Classifier: License :: OSI Approved :: MIT License
Classifier: Operating System :: OS Independent
Classifier: Programming Language :: Python :: 3
Classifier: Programming Language :: Python :: 3.8
Classifier: Programming Language :: Python :: 3.9
Classifier: Programming Language :: Python :: 3.10
Classifier: Programming Language :: Python :: 3.11
Classifier: Programming Language :: Python :: 3.12
Classifier: Programming Language :: Go
Classifier: Topic :: Internet :: WWW/HTTP :: HTTP Servers
Classifier: Topic :: Internet :: WWW/HTTP :: Dynamic Content
Classifier: Topic :: Software Development :: Libraries :: Python Modules
Classifier: Topic :: Software Development :: Libraries :: Application Frameworks
Classifier: Framework :: AsyncIO
Classifier: Framework :: FastAPI
Requires-Python: >=3.8
License-File: LICENSE
Requires-Dist: uvloop>=0.17.0; sys_platform != "win32"
Requires-Dist: pydantic>=2.0.0
Requires-Dist: typing-extensions>=4.0.0
Requires-Dist: starlette>=0.27.0
Requires-Dist: python-multipart>=0.0.5
Requires-Dist: email-validator>=2.0.0
Requires-Dist: httpx>=0.24.0
Requires-Dist: jinja2>=3.0.0
Requires-Dist: python-jose[cryptography]>=3.3.0
Requires-Dist: passlib[bcrypt]>=1.7.0
Requires-Dist: aiofiles>=23.0.0
Requires-Dist: websockets>=11.0.0
Provides-Extra: dev
Requires-Dist: pytest>=7.4.0; extra == "dev"
Requires-Dist: pytest-asyncio>=0.21.0; extra == "dev"
Requires-Dist: pytest-cov>=4.1.0; extra == "dev"
Requires-Dist: black>=23.7.0; extra == "dev"
Requires-Dist: isort>=5.12.0; extra == "dev"
Requires-Dist: flake8>=6.0.0; extra == "dev"
Requires-Dist: mypy>=1.5.0; extra == "dev"
Requires-Dist: pre-commit>=3.3.0; extra == "dev"
Requires-Dist: httpx>=0.24.0; extra == "dev"
Requires-Dist: requests>=2.31.0; extra == "dev"
Provides-Extra: full
Requires-Dist: uvloop>=0.17.0; sys_platform != "win32" and extra == "full"
Requires-Dist: pydantic>=2.0.0; extra == "full"
Requires-Dist: typing-extensions>=4.0.0; extra == "full"
Requires-Dist: starlette>=0.27.0; extra == "full"
Requires-Dist: python-multipart>=0.0.5; extra == "full"
Requires-Dist: email-validator>=2.0.0; extra == "full"
Requires-Dist: httpx>=0.24.0; extra == "full"
Requires-Dist: jinja2>=3.0.0; extra == "full"
Requires-Dist: python-jose[cryptography]>=3.3.0; extra == "full"
Requires-Dist: passlib[bcrypt]>=1.7.0; extra == "full"
Requires-Dist: aiofiles>=23.0.0; extra == "full"
Requires-Dist: websockets>=11.0.0; extra == "full"
Requires-Dist: redis>=4.6.0; extra == "full"
Requires-Dist: celery>=5.3.0; extra == "full"
Requires-Dist: prometheus-client>=0.17.0; extra == "full"
Requires-Dist: psutil>=5.9.0; extra == "full"
Requires-Dist: numpy>=1.24.0; extra == "full"
Requires-Dist: pandas>=2.0.0; extra == "full"
Provides-Extra: test
Requires-Dist: pytest>=7.4.0; extra == "test"
Requires-Dist: pytest-asyncio>=0.21.0; extra == "test"
Requires-Dist: pytest-cov>=4.1.0; extra == "test"
Requires-Dist: httpx>=0.24.0; extra == "test"
Requires-Dist: requests>=2.31.0; extra == "test"
Dynamic: license-file
